XStatic_Angular-1.8.2.2-nspkg.pth
xstatic/pkg/angular/__init__.py
xstatic/pkg/angular/data/angular-animate.js
xstatic/pkg/angular/data/angular-aria.js
xstatic/pkg/angular/data/angular-cookies.js
xstatic/pkg/angular/data/angular-csp.css
xstatic/pkg/angular/data/angular-loader.js
xstatic/pkg/angular/data/angular-message-format.js
xstatic/pkg/angular/data/angular-messages.js
xstatic/pkg/angular/data/angular-mocks.js
xstatic/pkg/angular/data/angular-parse-ext.js
xstatic/pkg/angular/data/angular-resource.js
xstatic/pkg/angular/data/angular-route.js
xstatic/pkg/angular/data/angular-sanitize.js
xstatic/pkg/angular/data/angular-touch.js
xstatic/pkg/angular/data/angular.js
xstatic/pkg/angular/data/errors.json
xstatic/pkg/angular/data/version.json
xstatic/pkg/angular/data/version.txt
XStatic_Angular-1.8.2.2.dist-info/LICENSE
XStatic_Angular-1.8.2.2.dist-info/METADATA
XStatic_Angular-1.8.2.2.dist-info/WHEEL
XStatic_Angular-1.8.2.2.dist-info/namespace_packages.txt
XStatic_Angular-1.8.2.2.dist-info/top_level.txt
XStatic_Angular-1.8.2.2.dist-info/RECORD
