Metadata-Version: 2.1
Name: XStatic-Angular
Version: 1.8.2.2
Summary: Angular 1.8.2 (XStatic packaging standard)
Home-page: http://angularjs.org
Maintainer: Rob Cresswell
Maintainer-email: robert.cresswell@outlook.com
License: MIT
Keywords: angular xstatic
Platform: any
